rlang/__init__.py
rlang/bor/__init__.py
rlang/bor/bridge.py
rlang/bor/crypto.py
rlang/bor/proofs.py
rlang/canonical/__init__.py
rlang/canonical/builder.py
rlang/canonical/primary_ir.py
rlang/cli/__init__.py
rlang/cli/rlangc.py
rlang/emitter/__init__.py
rlang/emitter/emitter.py
rlang/ir/__init__.py
rlang/ir/model.py
rlang/lexer/__init__.py
rlang/lexer/tokenizer.py
rlang/lexer/tokens.py
rlang/lowering/__init__.py
rlang/lowering/lowering.py
rlang/parser/__init__.py
rlang/parser/ast.py
rlang/parser/parser.py
rlang/semantic/__init__.py
rlang/semantic/resolver.py
rlang/semantic/symbols.py
rlang/types/__init__.py
rlang/types/type_checker.py
rlang/types/type_system.py
rlang/utils/__init__.py
rlang/utils/canonical_json.py
rlang_compiler-0.2.5.dist-info/licenses/LICENSE
rlang_compiler-0.2.5.dist-info/METADATA
rlang_compiler-0.2.5.dist-info/WHEEL
rlang_compiler-0.2.5.dist-info/entry_points.txt
rlang_compiler-0.2.5.dist-info/top_level.txt
rlang_compiler-0.2.5.dist-info/RECORD
