Metadata-Version: 2.4
Name: rlang-compiler
Version: 0.2.5
Summary: Deterministic RLang compiler with cryptographic proof generation for BoR (Blockchain of Reasoning)
Author: Kushagra Bhatnagar
License: MIT
Project-URL: Homepage, https://github.com/kushagrab21/Compiler_application
Project-URL: Documentation, https://github.com/kushagrab21/Compiler_application
Keywords: deterministic-compiler,bor,blockchain-of-reasoning,rlang,cryptographic-verification,proof-generation,verifiable-computation,dsl
Classifier: Programming Language :: Python :: 3
Classifier: Programming Language :: Python :: 3.9
Classifier: Programming Language :: Python :: 3.10
Classifier: Programming Language :: Python :: 3.11
Classifier: Programming Language :: Python :: 3.12
Classifier: Operating System :: OS Independent
Classifier: Development Status :: 4 - Beta
Classifier: Intended Audience :: Developers
Classifier: Intended Audience :: Science/Research
Classifier: Topic :: Software Development :: Compilers
Classifier: Topic :: Scientific/Engineering
Requires-Python: >=3.9
License-File: LICENSE
Provides-Extra: dev
Requires-Dist: black>=23.0.0; extra == "dev"
Requires-Dist: ruff>=0.1.0; extra == "dev"
Provides-Extra: test
Requires-Dist: pytest>=7.0.0; extra == "test"
Requires-Dist: pytest-cov>=4.0.0; extra == "test"
Provides-Extra: bor-sdk
Requires-Dist: bor-sdk>=1.0.0; extra == "bor-sdk"
Dynamic: license-file
